BoaConstrictor/BoaConstrictor.py
BoaConstrictor/__init__.py
BoaConstrictor/__main__.py
boaconstrictor-1.4.2.dist-info/METADATA
boaconstrictor-1.4.2.dist-info/WHEEL
boaconstrictor-1.4.2.dist-info/entry_points.txt
boaconstrictor-1.4.2.dist-info/top_level.txt
boaconstrictor-1.4.2.dist-info/RECORD
