Metadata-Version: 2.1
Name: boaconstrictor
Version: 1.4.2
Summary: Compiler for the BoaConstrictor programming language.
Home-page: https://github.com/thescribe11/BoaConstrictor
Author: Adam Raschio
Author-email: thescribe11@gmail.com
License: MIT
Platform: UNKNOWN
Classifier: License :: OSI Approved :: MIT License
Classifier: Programming Language :: Python :: 3
Classifier: Programming Language :: Python :: 3.7
Classifier: Development Status :: 5 - Production/Stable
Classifier: Environment :: Console
Classifier: Topic :: Software Development :: Compilers
Requires-Dist: pyinstaller
